alicona_converter/__init__.py
alicona_converter/__main__.py
alicona_converter/plot_surface.py
alicona_converter/py.typed
alicona_converter-1.0.10.dist-info/METADATA
alicona_converter-1.0.10.dist-info/WHEEL
alicona_converter-1.0.10.dist-info/top_level.txt
alicona_converter-1.0.10.dist-info/RECORD
